sqlalchemyplus/__init__.py
sqlalchemyplus/compiled/__init__.py
sqlalchemyplus/compiled/base.py
sqlalchemyplus/compiled/postgresql.py
sqlalchemyplus/sql/__init__.py
sqlalchemyplus/sql/ddl.py
sqlalchemyplus/sql/schema.py
sqlalchemy_plus-0.2.0.dist-info/LICENSE
sqlalchemy_plus-0.2.0.dist-info/METADATA
sqlalchemy_plus-0.2.0.dist-info/WHEEL
sqlalchemy_plus-0.2.0.dist-info/top_level.txt
sqlalchemy_plus-0.2.0.dist-info/RECORD
