Metadata-Version: 2.1
Name: sqlalchemy-plus
Version: 0.2.0
Summary: Create Views and Materialized Views with SqlAlchemy
Home-page: https://github.com/opus-42/sqlalchemy-plus
Author: Emmanuel Bavoux
Author-email: emmanuel.bavoux@gmail.com
License: UNKNOWN
Platform: UNKNOWN
Classifier: Programming Language :: Python :: 3
Classifier: Development Status :: 3 - Alpha
Classifier: License :: OSI Approved :: Apache Software License
Classifier: Operating System :: OS Independent
Requires-Dist: sqlalchemy (>=1.3.0)
